{
  "version": 1,
  "updated": "2026-04-20",
  "jobs": [
    {
      "id": "http-download-to-csv",
      "name": "HTTP Download → CSV-Mapping",
      "description": "Laedt eine CSV-Datei per HTTP herunter und fuehrt ein einfaches Feld-Mapping durch. Gutes Beispiel fuer den Pipeline-Aufbau mit DataMapping-Action.",
      "category": "Beispiel",
      "author": "Mixx IT",
      "version": "1.0",
      "minVersion": "1.0.0",
      "actions": 2,
      "path": "jobs/http-download-to-csv/job.mxjob"
    },
    {
      "id": "ftp-daily-sync",
      "name": "FTP Daily Sync",
      "description": "Holt taeglich um 06:00 alle neuen CSV-Dateien vom FTP-Server und speichert sie lokal im Archiv.",
      "category": "FTP",
      "author": "Mixx IT",
      "version": "1.0",
      "minVersion": "1.0.0",
      "actions": 2,
      "path": "jobs/ftp-daily-sync/job.mxjob"
    },
    {
      "id": "wartung-auto-update",
      "name": "Wartung: Auto-Update",
      "description": "Prueft woechentlich (Sonntag 03:00) auf neue Versionen und installiert sie automatisch. Der Dienst startet dabei kurz neu.",
      "category": "Wartung",
      "author": "Mixx IT",
      "version": "1.0",
      "minVersion": "1.0.22",
      "actions": 1,
      "path": "jobs/wartung-auto-update/job.mxjob"
    },
    {
      "id": "wartung-auto-backup",
      "name": "Wartung: Auto-Backup",
      "description": "Taegliches passwortgeschuetztes Backup aller Konfigurationen (FTP/DB/E-Mail/Jobs) um 02:00 Uhr mit 30 Tagen Aufbewahrung.",
      "category": "Wartung",
      "author": "Mixx IT",
      "version": "1.0",
      "minVersion": "1.0.28",
      "actions": 1,
      "path": "jobs/wartung-auto-backup/job.mxjob"
    },
    {
      "id": "lieferantenbestand-diff",
      "name": "Lieferantenbestand: Diff + Ameise",
      "description": "Taegliche Bestandsaktualisierung mit Diff-Optimierung und Struktur-Pruefung. Laedt CSV vom Lieferanten-FTP, mappt, vergleicht mit tliefartikel, importiert nur die geaenderten Zeilen via Ameise und sendet bei Fehler eine E-Mail.",
      "category": "JTL Integration",
      "author": "Mixx IT",
      "version": "1.0",
      "minVersion": "1.0.24",
      "actions": 6,
      "path": "jobs/lieferantenbestand-diff/job.mxjob"
    },
    {
      "id": "reports-bestand-export",
      "name": "Report: Bestand-Export",
      "description": "Taeglicher CSV-Export mit 3 Spalten (Artikelnummer, Artikelname, Bestand) aller aktiven Artikel auf einem bestimmten Warenlager. Keine Stuecklisten, Warenlager-ID per SQL-Variable konfigurierbar. Direkte DB-Abfrage ohne Ameise — schneller und skriptbar.",
      "category": "JTL-Reports",
      "author": "Mixx IT",
      "version": "1.1",
      "minVersion": "1.0.61",
      "actions": 1,
      "path": "jobs/reports-bestand-export/job.mxjob"
    },
    {
      "id": "jtl-dienst-watchdog",
      "name": "JTL-Dienst Watchdog",
      "description": "Prueft alle 5 Minuten den JTL-wawi-WorkerService und startet ihn automatisch neu, wenn er gestoppt ist. Sendet per E-Mail eine Benachrichtigung wenn eingegriffen wurde. Weitere JTL-Dienste koennen per ServiceMonitor-Aktion nach dem Import hinzugefuegt werden.",
      "category": "Wartung",
      "author": "Mixx IT",
      "version": "1.1",
      "minVersion": "1.0.58",
      "actions": 2,
      "path": "jobs/jtl-dienst-watchdog/job.mxjob"
    }
  ]
}
